scrapy_selenium/__init__.py
scrapy_selenium/http.py
scrapy_selenium/middlewares.py
scrapy_selenium-0.0.7.dist-info/METADATA
scrapy_selenium-0.0.7.dist-info/RECORD
scrapy_selenium-0.0.7.dist-info/WHEEL
scrapy_selenium-0.0.7.dist-info/top_level.txt
tests/__init__.py
tests/test_cases.py
tests/test_middlewares.py
