Metadata-Version: 1.0
Name: scrapy-selenium
Version: 0.0.7
Summary: Scrapy with selenium
Home-page: https://github.com/clemfromspace/scrapy-selenium
Author: UNKNOWN
Author-email: UNKNOWN
License: UNKNOWN
Platform: UNKNOWN
